lecturemd/__init__.py
lecturemd/__main__.py
lecturemd/platform.py
lecturemd/configure/__init__.py
lecturemd/configure/__main__.py
lecturemd/configure/configure.py
lecturemd/configure/configure.tcss
lecturemd/configure/ncl.tcss
lecturemd/make/__init__.py
lecturemd/make/__main__.py
lecturemd/make/make.py
lecturemd/make/filters/combine_lists.py
lecturemd/make/filters/definitions.py
lecturemd/make/filters/delistify.py
lecturemd/make/filters/derule.py
lecturemd/make/filters/examples.py
lecturemd/make/filters/format_filter.py
lecturemd/make/filters/html_tcolorbox.py
lecturemd/make/filters/latex_environments.py
lecturemd/make/filters/notesslides.py
lecturemd/make/filters/pandoc-crossref
lecturemd/make/filters/pandoc-crossref-mac
lecturemd/make/filters/pandoc-crossref.exe
lecturemd/make/filters/pause_before.py
lecturemd/make/filters/split_slides.py
lecturemd/make/filters/tabularray.py
lecturemd/make/post/tex_notes.py
lecturemd/make/post/tex_slides.py
lecturemd/new/__init__.py
lecturemd/new/__main__.py
lecturemd/new/new.py
lecturemd/new/styles/notes.css
lecturemd/new/styles/slides.css
lecturemd/new/templates/html_chunked.html
lecturemd/new/templates/html_notes.html
lecturemd/new/templates/html_slides.html
lecturemd/new/templates/latex_notes.tex
lecturemd/new/templates/latex_slides.tex
lecturemd/new/templates/latex_packages/common.sty
lecturemd/new/templates/latex_packages/descriptions.sty
lecturemd/new/templates/latex_packages/mathlabels.tex
lecturemd/new/templates/latex_packages/nicetables.sty
lecturemd/new/templates/latex_packages/notes.sty
lecturemd/new/templates/latex_packages/slides.sty
lecturemd/new/templates/latex_packages/tikzcard.sty
lecturemd-0.1.3.dist-info/LICENSE
lecturemd-0.1.3.dist-info/METADATA
lecturemd-0.1.3.dist-info/WHEEL
lecturemd-0.1.3.dist-info/entry_points.txt
lecturemd-0.1.3.dist-info/top_level.txt
lecturemd-0.1.3.dist-info/RECORD
