Metadata-Version: 2.2
Name: lecturemd
Version: 0.1.3
Summary: A system for generating lecture notes and slides from a single markdown file, for both HTML and PDF output.
Author: Peter Brookes Chambers
Project-URL: Homepage, https://github.com/ech0-chambers/lecturemd
Classifier: Programming Language :: Python :: 3
Classifier: License :: OSI Approved :: GNU Affero General Public License v3
Classifier: Operating System :: OS Independent
Requires-Python: >=3.8
License-File: LICENSE
Requires-Dist: textual
Requires-Dist: pyyaml
Requires-Dist: rich
Requires-Dist: pygmentation
Requires-Dist: pyndoc
